[
  {
    "ts": 1776468062.1725626,
    "sentiment": "neutral",
    "score": 0.0,
    "dominant_emotion": "neutral",
    "confidence": 0.5,
    "text_preview": "help me build an agent"
  },
  {
    "ts": 1776468121.6692483,
    "sentiment": "neutral",
    "score": 0.0,
    "dominant_emotion": "neutral",
    "confidence": 0.5,
    "text_preview": "help me build an agent"
  },
  {
    "ts": 1776472332.7068472,
    "sentiment": "neutral",
    "score": 0.0,
    "dominant_emotion": "neutral",
    "confidence": 0.5,
    "text_preview": "help me build an agent"
  },
  {
    "ts": 1776472381.0263324,
    "sentiment": "neutral",
    "score": 0.0,
    "dominant_emotion": "neutral",
    "confidence": 0.5,
    "text_preview": "help me build an agent"
  },
  {
    "ts": 1776472417.3287954,
    "sentiment": "neutral",
    "score": 0.0,
    "dominant_emotion": "neutral",
    "confidence": 0.5,
    "text_preview": "help me build an agent"
  },
  {
    "ts": 1776474078.248221,
    "sentiment": "neutral",
    "score": 0.0,
    "dominant_emotion": "neutral",
    "confidence": 0.5,
    "text_preview": "help me build an agent"
  },
  {
    "ts": 1776474584.0741537,
    "sentiment": "neutral",
    "score": 0.0,
    "dominant_emotion": "neutral",
    "confidence": 0.3,
    "text_preview": "Hi"
  },
  {
    "ts": 1776474586.5322862,
    "sentiment": "neutral",
    "score": 0.0,
    "dominant_emotion": "neutral",
    "confidence": 0.3,
    "text_preview": "Hi"
  },
  {
    "ts": 1776474587.1319895,
    "sentiment": "neutral",
    "score": 0.0,
    "dominant_emotion": "neutral",
    "confidence": 0.3,
    "text_preview": "Hi"
  },
  {
    "ts": 1776474587.7415857,
    "sentiment": "neutral",
    "score": 0.0,
    "dominant_emotion": "neutral",
    "confidence": 0.3,
    "text_preview": "Hi"
  },
  {
    "ts": 1776474588.3128872,
    "sentiment": "neutral",
    "score": 0.0,
    "dominant_emotion": "neutral",
    "confidence": 0.3,
    "text_preview": "Hi"
  },
  {
    "ts": 1776474588.8875947,
    "sentiment": "neutral",
    "score": 0.0,
    "dominant_emotion": "neutral",
    "confidence": 0.3,
    "text_preview": "Hi"
  },
  {
    "ts": 1776474710.426358,
    "sentiment": "neutral",
    "score": 0.0,
    "dominant_emotion": "neutral",
    "confidence": 0.3,
    "text_preview": "Hi"
  },
  {
    "ts": 1776474742.417041,
    "sentiment": "neutral",
    "score": 0.0,
    "dominant_emotion": "neutral",
    "confidence": 0.3,
    "text_preview": "Hi"
  },
  {
    "ts": 1776474804.339438,
    "sentiment": "neutral",
    "score": 0.0,
    "dominant_emotion": "neutral",
    "confidence": 0.3,
    "text_preview": "Hi"
  },
  {
    "ts": 1776474896.9783373,
    "sentiment": "neutral",
    "score": 0.0,
    "dominant_emotion": "neutral",
    "confidence": 0.3,
    "text_preview": "Hello"
  },
  {
    "ts": 1776474897.3456118,
    "sentiment": "neutral",
    "score": 0.0,
    "dominant_emotion": "neutral",
    "confidence": 0.3,
    "text_preview": "You alive"
  },
  {
    "ts": 1776474897.6754913,
    "sentiment": "neutral",
    "score": 0.0,
    "dominant_emotion": "neutral",
    "confidence": 0.3,
    "text_preview": "Hi"
  },
  {
    "ts": 1776474930.9502835,
    "sentiment": "neutral",
    "score": 0.0,
    "dominant_emotion": "neutral",
    "confidence": 0.5,
    "text_preview": "Like what?"
  },
  {
    "ts": 1776474984.6191435,
    "sentiment": "neutral",
    "score": 0.0,
    "dominant_emotion": "neutral",
    "confidence": 0.3,
    "text_preview": "Hi"
  },
  {
    "ts": 1776475089.118966,
    "sentiment": "neutral",
    "score": 0.0,
    "dominant_emotion": "neutral",
    "confidence": 0.3,
    "text_preview": "Hi"
  },
  {
    "ts": 1776475114.5420098,
    "sentiment": "neutral",
    "score": 0.0,
    "dominant_emotion": "neutral",
    "confidence": 0.5,
    "text_preview": "Build what?"
  },
  {
    "ts": 1776475689.2724068,
    "sentiment": "neutral",
    "score": 0.0,
    "dominant_emotion": "neutral",
    "confidence": 0.3,
    "text_preview": "Do I have anything running in pm2"
  },
  {
    "ts": 1776475744.782029,
    "sentiment": "neutral",
    "score": 0.0,
    "dominant_emotion": "neutral",
    "confidence": 0.5,
    "text_preview": "What is in pm2 tho any process stopped"
  },
  {
    "ts": 1776475809.0091214,
    "sentiment": "neutral",
    "score": 0.0,
    "dominant_emotion": "neutral",
    "confidence": 0.3,
    "text_preview": "I never told you to start it"
  },
  {
    "ts": 1776475839.292657,
    "sentiment": "neutral",
    "score": 0.0,
    "dominant_emotion": "neutral",
    "confidence": 0.3,
    "text_preview": "Stop all pm2 processes"
  },
  {
    "ts": 1776475996.0991526,
    "sentiment": "neutral",
    "score": 0.0,
    "dominant_emotion": "neutral",
    "confidence": 0.3,
    "text_preview": "I want you to massage me"
  },
  {
    "ts": 1776476052.7183204,
    "sentiment": "neutral",
    "score": 0.0,
    "dominant_emotion": "neutral",
    "confidence": 0.3,
    "text_preview": "Do you talk"
  },
  {
    "ts": 1776476066.972503,
    "sentiment": "neutral",
    "score": 0.0,
    "dominant_emotion": "neutral",
    "confidence": 0.3,
    "text_preview": "Send me voice note"
  },
  {
    "ts": 1776476103.2732933,
    "sentiment": "neutral",
    "score": 0.0,
    "dominant_emotion": "neutral",
    "confidence": 0.3,
    "text_preview": "No I still didn\u2019t sleep"
  },
  {
    "ts": 1776476245.766225,
    "sentiment": "neutral",
    "score": 0.0,
    "dominant_emotion": "neutral",
    "confidence": 0.5,
    "text_preview": "help me build an agent"
  }
]